redmq/__init__.py
redmq/lock.py
redmq/message_queue.py
redmq/requests_server.py
redmq/schedule.py
redmq-0.2.2.dist-info/licenses/LICENSE
redmq-0.2.2.dist-info/METADATA
redmq-0.2.2.dist-info/WHEEL
redmq-0.2.2.dist-info/entry_points.txt
redmq-0.2.2.dist-info/top_level.txt
redmq-0.2.2.dist-info/RECORD
