Metadata-Version: 2.4
Name: redmq
Version: 0.2.2
Summary: Redis message queue utils: a simple distributed lock based on redis, a simple message queue based on redis with ack feature.
Author: rRR0VrFP
Maintainer: rRR0VrFP
License: MIT
Keywords: redmq
Classifier: Development Status :: 5 - Production/Stable
Classifier: Intended Audience :: Developers
Classifier: Topic :: Software Development :: Libraries :: Python Modules
Classifier: License :: OSI Approved :: MIT License
Classifier: Programming Language :: Python :: 3
Classifier: Programming Language :: Python :: 3 :: Only
License-File: LICENSE
Requires-Dist: redis
Requires-Dist: bizerror
Requires-Dist: requests
Requires-Dist: fastutils
Requires-Dist: daemon-application
Requires-Dist: croniter
Dynamic: author
Dynamic: classifier
Dynamic: description
Dynamic: description-content-type
Dynamic: keywords
Dynamic: license
Dynamic: license-file
Dynamic: maintainer
Dynamic: requires-dist
Dynamic: summary
